teleads/__init__.py
teleads/_aiogram.py
teleads/_aiogram3.py
teleads/_bap.py
TeleAds-0.1.4.dist-info/LICENSE
TeleAds-0.1.4.dist-info/METADATA
TeleAds-0.1.4.dist-info/WHEEL
TeleAds-0.1.4.dist-info/top_level.txt
TeleAds-0.1.4.dist-info/RECORD
